organizer/__init__.py
organizer/organizer.py
download_organizer-1.6.dist-info/LICENSE
download_organizer-1.6.dist-info/METADATA
download_organizer-1.6.dist-info/WHEEL
download_organizer-1.6.dist-info/entry_points.txt
download_organizer-1.6.dist-info/top_level.txt
download_organizer-1.6.dist-info/RECORD
