Metadata-Version: 2.1
Name: download-organizer
Version: 1.6
Summary: A Python script to organize your downloads folder by file extensions and watch for new files.
Home-page: https://github.com/at-pyrix/download-organizer
Author: pyrix
Classifier: Development Status :: 3 - Alpha
Classifier: Intended Audience :: End Users/Desktop
Classifier: License :: OSI Approved :: GNU General Public License v3 (GPLv3)
Classifier: Programming Language :: Python :: 3
Classifier: Programming Language :: Python :: 3.8
Classifier: Programming Language :: Python :: 3.9
Classifier: Programming Language :: Python :: 3.10
Classifier: Programming Language :: Python :: 3.11
Requires-Python: >=3.6
License-File: LICENSE
Requires-Dist: colorama
